morphosamplers/__init__.py
morphosamplers/core.py
morphosamplers/helical_filament.py
morphosamplers/preprocess.py
morphosamplers/sample_types.py
morphosamplers/sampler.py
morphosamplers/spline.py
morphosamplers/surface_spline.py
morphosamplers/utils.py
morphosamplers/models/__init__.py
morphosamplers/models/dipole.py
morphosamplers/models/path.py
morphosamplers/models/sphere.py
morphosamplers/models/surface.py
morphosamplers/samplers/__init__.py
morphosamplers/samplers/dipole_samplers/__init__.py
morphosamplers/samplers/dipole_samplers/disk_sampler.py
morphosamplers/samplers/dipole_samplers/pose_sampler.py
morphosamplers/samplers/path_samplers/__init__.py
morphosamplers/samplers/path_samplers/point_sampler.py
morphosamplers/samplers/path_samplers/pose_sampler_helical.py
morphosamplers/samplers/path_samplers/pose_sampler_parallel.py
morphosamplers/samplers/path_samplers/pose_sampler_rings.py
morphosamplers/samplers/sphere_samplers/__init__.py
morphosamplers/samplers/sphere_samplers/_sphere_utils.py
morphosamplers/samplers/sphere_samplers/point_sampler.py
morphosamplers/samplers/sphere_samplers/pose_sampler.py
morphosamplers-0.0.16.dist-info/licenses/LICENSE
morphosamplers-0.0.16.dist-info/METADATA
morphosamplers-0.0.16.dist-info/WHEEL
morphosamplers-0.0.16.dist-info/top_level.txt
morphosamplers-0.0.16.dist-info/RECORD
